fileformats/extras/medimage/__init__.py
fileformats/extras/medimage/_version.py
fileformats/extras/medimage/base.py
fileformats/extras/medimage/converters.py
fileformats/extras/medimage/dicom.py
fileformats/extras/medimage/diffusion.py
fileformats/extras/medimage/nifti.py
fileformats/extras/medimage/tests/test_deidentify.py
fileformats/extras/medimage/tests/test_generators.py
fileformats/extras/medimage/tests/test_neuro_converters.py
fileformats_medimage_extras-0.11.0.dist-info/METADATA
fileformats_medimage_extras-0.11.0.dist-info/WHEEL
fileformats_medimage_extras-0.11.0.dist-info/licenses/LICENSE
fileformats_medimage_extras-0.11.0.dist-info/RECORD
